LICENSE.txt
MANIFEST.in
README.txt
setup.py
pcart_comparison/__init__.py
pcart_comparison/admin.py
pcart_comparison/apps.py
pcart_comparison/models.py
pcart_comparison/urls.py
pcart_comparison/views.py
pcart_comparison.egg-info/PKG-INFO
pcart_comparison.egg-info/SOURCES.txt
pcart_comparison.egg-info/dependency_links.txt
pcart_comparison.egg-info/not-zip-safe
pcart_comparison.egg-info/requires.txt
pcart_comparison.egg-info/top_level.txt
pcart_comparison/locale/ru/LC_MESSAGES/django.mo
pcart_comparison/locale/ru/LC_MESSAGES/django.po
pcart_comparison/locale/uk/LC_MESSAGES/django.mo
pcart_comparison/locale/uk/LC_MESSAGES/django.po
pcart_comparison/migrations/0001_initial.py
pcart_comparison/migrations/__init__.py